Metadata-Version: 2.1
Name: ghostbusterV3
Version: 0.0.9
Summary: Eliminate dangling elastic IPs by performing analysis on your resources within all your AWS accounts.
Home-page: https://gitlab.urbanclap.com/urbanclap/dangling-dns-service/tree/ghostbuster_merge
Author: yashbharadwaj
Author-email: yashbharadwaj@urbancompany.com
License: Apache Software License 2.0
Platform: UNKNOWN
Classifier: Development Status :: 3 - Alpha
Classifier: Intended Audience :: Developers
Classifier: Topic :: Software Development :: Libraries
Classifier: License :: OSI Approved :: GNU Affero General Public License v3
Classifier: Programming Language :: Python :: 3.8
Requires-Python: >=0.0.1
License-File: LICENSE
